neclib/__init__.py
neclib/controllers/__init__.py
neclib/controllers/antenna_pid.py
neclib/coordinates/__init__.py
neclib/coordinates/convert.py
neclib/coordinates/frame.py
neclib/coordinates/observations/__init__.py
neclib/coordinates/observations/observation_spec_base.py
neclib/coordinates/observations/optical_pointing.py
neclib/coordinates/observations/otf.py
neclib/coordinates/observations/radio_pointing.py
neclib/coordinates/observer.py
neclib/coordinates/optimize.py
neclib/coordinates/path_finder.py
neclib/coordinates/paths/__init__.py
neclib/coordinates/paths/linear.py
neclib/coordinates/paths/path_base.py
neclib/coordinates/paths/track.py
neclib/coordinates/pointing_error/__init__.py
neclib/coordinates/pointing_error/nanten2.py
neclib/coordinates/pointing_error/omu1p85m.py
neclib/coordinates/pointing_error/pointing_error.py
neclib/core/__init__.py
neclib/core/configuration.py
neclib/core/data_type/__init__.py
neclib/core/data_type/ordinal.py
neclib/core/data_type/parameters.py
neclib/core/data_type/rich_parameters.py
neclib/core/data_type/status_manager.py
neclib/core/data_type/value_range.py
neclib/core/environ.py
neclib/core/exceptions.py
neclib/core/files/__init__.py
neclib/core/files/general.py
neclib/core/files/toml.py
neclib/core/formatting/__init__.py
neclib/core/formatting/dict_to_html.py
neclib/core/formatting/observation_to_html.py
neclib/core/formatting/status_to_html.py
neclib/core/inform/__init__.py
neclib/core/inform/console_logger.py
neclib/core/inform/deprecation.py
neclib/core/inform/disable.py
neclib/core/math/__init__.py
neclib/core/math/clip_impl.py
neclib/core/math/frange_impl.py
neclib/core/math/functions.py
neclib/core/math/random.py
neclib/core/normalization/__init__.py
neclib/core/normalization/array.py
neclib/core/normalization/astropy.py
neclib/core/normalization/function_defaults.py
neclib/core/security/__init__.py
neclib/core/security/busy_impl.py
neclib/core/security/load_check.py
neclib/core/security/sanitize_impl.py
neclib-1.0.2.dist-info/LICENSE
neclib-1.0.2.dist-info/METADATA
neclib-1.0.2.dist-info/WHEEL
neclib-1.0.2.dist-info/RECORD
