Metadata-Version: 2.3
Name: neclib
Version: 1.0.2
Summary: Pure Python tools for NECST.
License: MIT
Author: KaoruNishikawa
Author-email: k.nishikawa@a.phys.nagoya-u.ac.jp
Requires-Python: >=3.9,<3.13
Classifier: License :: OSI Approved :: MIT License
Classifier: Programming Language :: Python :: 3
Classifier: Programming Language :: Python :: 3.9
Classifier: Programming Language :: Python :: 3.10
Classifier: Programming Language :: Python :: 3.11
Classifier: Programming Language :: Python :: 3.12
Requires-Dist: astropy (>=5.3,<6.0)
Requires-Dist: matplotlib (>=3.6.2,<4.0.0)
Requires-Dist: necstdb (>=0.2.9,<0.3.0)
Requires-Dist: numpy (==1.26.4)
Requires-Dist: ogameasure (>=0.6.1,<0.7.0)
Requires-Dist: pandas (<2.0)
Requires-Dist: psutil (>=5.9.4,<6.0.0)
Requires-Dist: pyerfa (>=2.0.0.3,<3.0.0.0)
Requires-Dist: pyinterface (>=1.7.5,<2.0.0) ; sys_platform == "linux"
Requires-Dist: scipy (>=1.11.3,<2.0.0)
Requires-Dist: tomlkit (>=0.11.4,<0.12.0)
Requires-Dist: xfftspy (>=0.1.3,<0.2.0)
Project-URL: Homepage, https://necst-telescope.github.io/neclib/
Project-URL: Repository, https://github.com/necst-telescope/neclib
